misfits/__init__.py
misfits/app.py
misfits/data.py
misfits/headers.py
misfits/log.py
misfits/logo.py
misfits/misfits.tcss
misfits/mtypes.py
misfits/screens.py
misfits/suggester.py
misfits/utils.py
misfits-0.1.1.dist-info/METADATA
misfits-0.1.1.dist-info/WHEEL
misfits-0.1.1.dist-info/entry_points.txt
misfits-0.1.1.dist-info/licenses/LICENSE.txt
misfits-0.1.1.dist-info/RECORD
