Metadata-Version: 2.4
Name: misfits
Version: 0.1.1
Summary: A FITS table viewer for the terminal.
Project-URL: Homepage, https://github.com/peppedilillo/misfits
Author-email: Giuseppe Dilillo <peppedilillo@gmail.com>
License:                     GNU GENERAL PUBLIC LICENSE
License-File: LICENSE.txt
Keywords: Astrophysics,FITS,Flexible Image Transport System
Classifier: License :: OSI Approved :: MIT License
Classifier: Operating System :: OS Independent
Classifier: Programming Language :: Python :: 3
Classifier: Programming Language :: Python :: 3.11
Classifier: Programming Language :: Python :: 3.12
Classifier: Programming Language :: Python :: 3.13
Requires-Python: >=3.11
Requires-Dist: astropy==7.1.0
Requires-Dist: click==8.2.1
Requires-Dist: pandas==2.3.0
Requires-Dist: terminaltexteffects==0.12.0
Requires-Dist: textual==3.5.0
Provides-Extra: dev
Requires-Dist: black>=24.8; extra == 'dev'
Requires-Dist: ipython>=8.27; extra == 'dev'
Requires-Dist: isort>=5.13; extra == 'dev'
Requires-Dist: mypy>=1.11; extra == 'dev'
Requires-Dist: textual-dev>=1.5; extra == 'dev'
